arbitrum_py/__init__.py
arbitrum_py/asset_bridger/__init__.py
arbitrum_py/asset_bridger/asset_bridger.py
arbitrum_py/asset_bridger/erc20_bridger.py
arbitrum_py/asset_bridger/eth_bridger.py
arbitrum_py/asset_bridger/l1_l3_bridger.py
arbitrum_py/data_entities/__init__.py
arbitrum_py/data_entities/address.py
arbitrum_py/data_entities/constants.py
arbitrum_py/data_entities/errors.py
arbitrum_py/data_entities/event.py
arbitrum_py/data_entities/message.py
arbitrum_py/data_entities/networks.py
arbitrum_py/data_entities/retryable_data.py
arbitrum_py/data_entities/rpc.py
arbitrum_py/data_entities/signer_or_provider.py
arbitrum_py/data_entities/transaction_request.py
arbitrum_py/inbox/__init__.py
arbitrum_py/inbox/inbox.py
arbitrum_py/message/__init__.py
arbitrum_py/message/child_to_parent_message.py
arbitrum_py/message/child_to_parent_message_classic.py
arbitrum_py/message/child_to_parent_message_nitro.py
arbitrum_py/message/child_transaction.py
arbitrum_py/message/message_data_parser.py
arbitrum_py/message/parent_to_child_message.py
arbitrum_py/message/parent_to_child_message_creator.py
arbitrum_py/message/parent_to_child_message_gas_estimator.py
arbitrum_py/message/parent_transaction.py
arbitrum_py/utils/__init__.py
arbitrum_py/utils/arb_provider.py
arbitrum_py/utils/byte_serialize_params.py
arbitrum_py/utils/calldata.py
arbitrum_py/utils/event_fetcher.py
arbitrum_py/utils/helper.py
arbitrum_py/utils/lib.py
arbitrum_py/utils/multicall.py
scripts/__init__.py
scripts/gen_network.py
scripts/setup_common.py
scripts/test_setup.py
tests/__init__.py
tests/integration/__init__.py
tests/integration/child_transaction_receipt_test.py
tests/integration/custom_erc20_test.py
tests/integration/eth_test.py
tests/integration/get_arbitrum_network_information_from_rollup_test.py
tests/integration/l1_l3_bridger_test.py
tests/integration/parent_to_child_message_creator_test.py
tests/integration/parent_to_child_message_gas_estimator_test.py
tests/integration/retryable_data_test.py
arbitrum_sdk-0.2.1.dist-info/LICENSE.md
arbitrum_sdk-0.2.1.dist-info/METADATA
arbitrum_sdk-0.2.1.dist-info/WHEEL
arbitrum_sdk-0.2.1.dist-info/top_level.txt
arbitrum_sdk-0.2.1.dist-info/RECORD
